dashai_img_mlp_plugin/__init__.py
dashai_img_mlp_plugin/dataloader_class_template.py
dashai_img_mlp_plugin/metric_class_template.py
dashai_img_mlp_plugin/model_class_template.py
dashai_img_mlp_plugin/task_class_template.py
dashai_img_mlp_plugin-0.0.2.dist-info/METADATA
dashai_img_mlp_plugin-0.0.2.dist-info/WHEEL
dashai_img_mlp_plugin-0.0.2.dist-info/entry_points.txt
dashai_img_mlp_plugin-0.0.2.dist-info/RECORD
